{
  "$schema": "http://json-schema.org/draft-07/schema#",
  "title": "Forge TypeLayer l10n Bundle",
  "description": "Source of Truth for extension translations. Defines all allowed keys and their context.",
  "type": "object",
  "required": [
    "mode.off", "mode.manual", "mode.auto",
    "status.bar.ready", "status.bar.watching",
    "msg.noActiveEditor", "msg.noWorkspaceFolder", "msg.modeChanged", "msg.runtimeInfo",
    "doctor.title", "doctor.ok", "doctor.runtime",
    "prompt.gitignore", "prompt.gitignore.yes", "prompt.gitignore.no",
    "prompt.strategy.title", "prompt.strategy.full", "prompt.strategy.domain", "prompt.strategy.recursive", "prompt.strategy.standalone",
    "error.binaryNotFound", "error.batchFailed", "error.batchMessage", "error.bundlerFailed",
    "error.preflight.binary", "error.preflight.filesystem",
    "info.compiling", "info.gitignoreAdded", "info.batchStarted", "info.activated",
    "success.extracted",
    "warn.orphan", "warn.zeroExtracted", "warn.outdatedBinary"
  ],
  "properties": {
    "$schema": { "type": "string", "description": "Pointer to the l10n schema." },
    "mode.off": { "type": "string", "description": "Label for 'OFF' mode in the status bar and picker." },
    "mode.manual": { "type": "string", "description": "Label for 'MANUAL' mode." },
    "mode.auto": { "type": "string", "description": "Label for 'AUTO' mode." },
    "status.bar.ready": { "type": "string", "description": "Tooltip when the current file is a valid source ready for emission." },
    "status.bar.watching": { "type": "string", "description": "Tooltip when Forge is active but the current file is not an entry." },
    "msg.noActiveEditor": { "type": "string", "description": "Shown when the user triggers a command without an open file." },
    "msg.noWorkspaceFolder": { "type": "string", "description": "Shown when the user triggers a command outside a workspace." },
    "msg.modeChanged": { "type": "string", "description": "Status notification when the mode is changed. Uses {0} for the new mode." },
    "msg.runtimeInfo": { "type": "string", "description": "Notification about the selected compiler. {0}=Runtime, {1}=Reason." },
    "doctor.title": { "type": "string", "description": "Title for the Doctor report." },
    "doctor.ok": { "type": "string", "description": "Report status when no issues are found." },
    "doctor.warningPrefix": { "type": "string", "description": "Header for the warnings list in the Doctor report." },
    "doctor.runtime": { "type": "string", "description": "Section header for the detected runtime. Uses {0}." },
    "doctor.lint": { "type": "string", "description": "Section header for the detected lint strategy. Uses {0}." },
    "doctor.manifest": { "type": "string", "description": "Section header for the detected entries file. Uses {0}." },
    "doctor.hints": { "type": "string", "description": "Section header for the detected config hints. Uses {0}." },
    "status.bar.suffix.forge": { "type": "string", "description": "Default suffix .forge.ts" },
    "status.bar.suffix.source": { "type": "string", "description": "Default suffix .source.ts" },
    "status.bar.suffix.f": { "type": "string", "description": "Default suffix .f.ts" },
    "prompt.gitignore": { "type": "string", "description": "Question asked to add forge-temp to .gitignore." },
    "prompt.gitignore.yes": { "type": "string", "description": "Positive answer for gitignore prompt." },
    "prompt.gitignore.no": { "type": "string", "description": "Negative answer for gitignore prompt." },
    "prompt.strategy.title": { "type": "string", "description": "QuickPick title for selecting build strategy." },
    "prompt.strategy.full": { "type": "string", "description": "Label for FULL_BUNDLE strategy." },
    "prompt.strategy.domain": { "type": "string", "description": "Label for DOMAIN_BUNDLE strategy." },
    "prompt.strategy.recursive": { "type": "string", "description": "Label for RECURSIVE_PURE strategy." },
    "prompt.strategy.standalone": { "type": "string", "description": "Label for STANDALONE strategy." },
    "error.binaryNotFound": { "type": "string", "description": "Error when bun/deno/tsc are all missing from PATH." },
    "info.compiling": { "type": "string", "description": "Log message when a batch build starts. Uses {0} for file count." },
    "success.extracted": { "type": "string", "description": "Log message when a batch build finishes. {0}=Files, {1}=Elapsed ms." },
    "warn.orphan": { "type": "string", "description": "Warning when an import leads to a missing artifact. Uses {0}." },
    "info.gitignoreAdded": { "type": "string", "description": "Log when .gitignore is successfully updated." },
    "info.batchStarted": { "type": "string", "description": "Visual separator for the start of a compilation log." },
    "warn.zeroExtracted": { "type": "string", "description": "Warning when a build finished but produced no files." },
    "error.batchFailed": { "type": "string", "description": "Header for a failed batch build log." },
    "error.batchMessage": { "type": "string", "description": "Generic VS Code error notification for batch failures. Uses {0}." },
    "error.bundlerFailed": { "type": "string", "description": "Deep error message when the bundler binary returns non-zero. Uses {0}." },
    "error.preflight.binary": { "type": "string", "description": "Error when a binary is found but fails execution test. Uses {0}." },
    "error.preflight.filesystem": { "type": "string", "description": "Error when the shadow directory is not writable. Uses {0}." },
    "config.warn.nonStringSuffix": { "type": "string", "description": "Log when a non-string entry is found in lockSuffixes." },
    "config.warn.invalidSuffix": { "type": "string", "description": "Log when a suffix doesn't follow the .*.ts pattern." },
    "config.warn.duplicateSuffix": { "type": "string", "description": "Log when a duplicate suffix is defined in config." },
    "config.warn.allInvalidSuffixes": { "type": "string", "description": "Log describing fallback to defaults when all config suffixes are invalid." },
    "info.activated": { "type": "string", "description": "Greeting log when the extension initializes." },
    "warn.outdatedBinary": { "type": "string", "description": "Warning when a binary (Bun/Deno/TSC) is found but its version is below the compatibility registry requirements. {0}=Binary name, {1}=Current Version, {2}=Required Version." }
  },
  "additionalProperties": false
}
